bbsearch/__init__.py
bbsearch/api/__init__.py
bbsearch/api/programs.py
bbsearch/client.py
bbsearch/errors.py
bbsearch/manager.py
bbsearch/models/__init__.py
bbsearch/models/http_validation_error.py
bbsearch/models/program.py
bbsearch/models/program_scope.py
bbsearch/models/programs.py
bbsearch/models/types.py
bbsearch/models/validation_error.py
bbsearch/py.typed
bbsearch-0.0.0.dist-info/WHEEL
bbsearch-0.0.0.dist-info/METADATA
bbsearch-0.0.0.dist-info/RECORD
