Metadata-Version: 2.1
Name: bbsearch
Version: 0.0.0
Summary: A client library and CLI for accessing the Bug Bounty Search API
Requires-Python: >=3.8,<4.0
Classifier: Programming Language :: Python :: 3
Classifier: Programming Language :: Python :: 3.8
Requires-Dist: httpx (>=0.13.3,<0.14.0)
